v2root/__init__.py
v2root/v2root.py
v2root/lib/Makefile.linux
v2root/lib/Makefile.win
v2root/lib/v2ray
v2root/lib/v2ray.exe
v2root/lib/build_linux/libv2root.so
v2root/lib/build_linux/libv2root_core.o
v2root/lib/build_linux/libv2root_linux.o
v2root/lib/build_linux/libv2root_manage.o
v2root/lib/build_linux/libv2root_service.o
v2root/lib/build_linux/libv2root_shadowsocks.o
v2root/lib/build_linux/libv2root_utils.o
v2root/lib/build_linux/libv2root_vless.o
v2root/lib/build_linux/libv2root_vmess.o
v2root/lib/build_win/libcjson-1.dll
v2root/lib/build_win/libjansson-4.dll
v2root/lib/build_win/libv2root.dll
v2root/lib/build_win/libv2root_core.o
v2root/lib/build_win/libv2root_manage.o
v2root/lib/build_win/libv2root_shadowsocks.o
v2root/lib/build_win/libv2root_utils.o
v2root/lib/build_win/libv2root_vless.o
v2root/lib/build_win/libv2root_vmess.o
v2root/lib/build_win/libv2root_win.o
v2root/lib/build_win/libwinpthread-1.dll
v2root/lib/src/cJSON.h
v2root/lib/src/libv2root_common.h
v2root/lib/src/libv2root_core.c
v2root/lib/src/libv2root_core.h
v2root/lib/src/libv2root_linux.c
v2root/lib/src/libv2root_linux.h
v2root/lib/src/libv2root_manage.c
v2root/lib/src/libv2root_manage.h
v2root/lib/src/libv2root_service.c
v2root/lib/src/libv2root_service.h
v2root/lib/src/libv2root_shadowsocks.c
v2root/lib/src/libv2root_shadowsocks.h
v2root/lib/src/libv2root_utils.c
v2root/lib/src/libv2root_utils.h
v2root/lib/src/libv2root_vless.c
v2root/lib/src/libv2root_vless.h
v2root/lib/src/libv2root_vmess.c
v2root/lib/src/libv2root_vmess.h
v2root/lib/src/libv2root_win.c
v2root/lib/src/libv2root_win.h
v2root/lib/src/pwd.h
v2root-1.1.2.dist-info/licenses/LICENSE
v2root-1.1.2.dist-info/METADATA
v2root-1.1.2.dist-info/WHEEL
v2root-1.1.2.dist-info/top_level.txt
v2root-1.1.2.dist-info/RECORD
